MDRMF/__init__.py
MDRMF/configvalidator.py
MDRMF/dataset.py
MDRMF/datasetflagged.py
MDRMF/evaluator.py
MDRMF/experimenter.py
MDRMF/featurizer.py
MDRMF/model.py
MDRMF/moleculeloader.py
MDRMF/models/__init__.py
MDRMF/models/engine.py
MDRMF/models/modeller.py
MDRMF/schemas/Experiment_schema.yaml
MDRMF/schemas/__init__.py
MDRMF/schemas/create_dataset_schema.yaml
MDRMF/schemas/labelExperiment_schema.yaml
MDRMF/schemas/unique_initial_sample_schema.yaml
MDRMF-0.0.13.dist-info/METADATA
MDRMF-0.0.13.dist-info/WHEEL
MDRMF-0.0.13.dist-info/top_level.txt
MDRMF-0.0.13.dist-info/RECORD
