Metadata-Version: 2.1
Name: MDRMF
Version: 0.0.13
Summary: Multidrug Resistance Machine Fishing
Home-page: https://github.com/MolinDiscovery/MDRMF
Author: Jacob Molin Nielsen
Author-email: jacob.molin@me.com
Keywords: machine fishing,drug discovery,machine learning,pool based active learning
Requires-Dist: joblib
Requires-Dist: lightgbm
Requires-Dist: matplotlib
Requires-Dist: numpy
Requires-Dist: pandas
Requires-Dist: pykwalify
Requires-Dist: pyyaml
Requires-Dist: rdkit
Requires-Dist: scipy
Requires-Dist: scikit-learn
